[
  {
    "name": "งานเตรียมการ - Site Preparation",
    "description": "แบบฟอร์มตรวจสอบงานเตรียมการก่อนเริ่มก่อสร้าง",
    "category": "preparation",
    "items": [
      {
        "title": "ตรวจสอบการปักหลักแนวเขต",
        "description": "ตรวจสอบว่าได้มีการปักหลักแนวเขตที่ดินถูกต้องตามแบบ",
        "category": "site_setup",
        "stage": "pre",
        "order": 1
      },
      {
        "title": "ตรวจสอบป้ายโครงการและป้ายความปลอดภัย",
        "description": "ตรวจสอบการติดตั้งป้ายโครงการและป้ายเตือนความปลอดภัยครบถ้วน",
        "category": "site_setup",
        "stage": "pre",
        "order": 2
      },
      {
        "title": "ตรวจสอบรั้วกั้นพื้นที่ก่อสร้าง",
        "description": "ตรวจสอบความมั่นคงและความสูงของรั้วกั้นรอบพื้นที่",
        "category": "safety",
        "stage": "pre",
        "order": 3
      },
      {
        "title": "ตรวจสอบสถานที่เก็บวัสดุและอุปกรณ์",
        "description": "ตรวจสอบพื้นที่จัดเก็บวัสดุและอุปกรณ์ก่อสร้างเป็นระเบียบ",
        "category": "site_setup",
        "stage": "in_progress",
        "order": 4
      },
      {
        "title": "ตรวจสอบระบบไฟฟ้าชั่วคราว",
        "description": "ตรวจสอบการติดตั้งระบบไฟฟ้าชั่วคราวและความปลอดภัย",
        "category": "utilities",
        "stage": "in_progress",
        "order": 5
      },
      {
        "title": "ตรวจสอบระบบน้ำชั่วคราว",
        "description": "ตรวจสอบการจัดหาน้ำสะอาดและระบบระบายน้ำ",
        "category": "utilities",
        "stage": "in_progress",
        "order": 6
      },
      {
        "title": "ตรวจสอบสุขาชั่วคราว",
        "description": "ตรวจสอบความสะอาดและจำนวนห้องสุขาชั่วคราว",
        "category": "facilities",
        "stage": "post",
        "order": 7
      },
      {
        "title": "ตรวจสอบความสะอาดของพื้นที่",
        "description": "ตรวจสอบความสะอาดและการจัดเก็บขยะในพื้นที่ก่อสร้าง",
        "category": "cleanliness",
        "stage": "post",
        "order": 8
      }
    ]
  },
  {
    "name": "งานโครงสร้าง - Structural Work",
    "description": "แบบฟอร์มตรวจสอบงานโครงสร้างคอนกรีต",
    "category": "structural",
    "items": [
      {
        "title": "ตรวจสอบแบบก่อสร้างและรายละเอียด",
        "description": "ตรวจสอบความถูกต้องของแบบก่อสร้างและรายละเอียดโครงสร้าง",
        "category": "documentation",
        "stage": "pre",
        "order": 1
      },
      {
        "title": "ตรวจสอบการวางผังแนวเสา",
        "description": "ตรวจสอบตำแหน่งและแนวเสาตามแบบก่อสร้าง",
        "category": "layout",
        "stage": "pre",
        "order": 2
      },
      {
        "title": "ตรวจสอบคุณภาพเหล็กเสริม",
        "description": "ตรวจสอบขนาด เกรด และสภาพของเหล็กเสริม",
        "category": "material",
        "stage": "pre",
        "order": 3
      },
      {
        "title": "ตรวจสอบการจัดเหล็กเสริมเสา",
        "description": "ตรวจสอบขนาด ระยะห่าง และการผูกเหล็กเสริมเสา",
        "category": "reinforcement",
        "stage": "in_progress",
        "order": 4
      },
      {
        "title": "ตรวจสอบการจัดเหล็กเสริมคาน",
        "description": "ตรวจสอบขนาด ระยะห่าง และการผูกเหล็กเสริมคาน",
        "category": "reinforcement",
        "stage": "in_progress",
        "order": 5
      },
      {
        "title": "ตรวจสอบการจัดเหล็กเสริมพื้น",
        "description": "ตรวจสอบขนาด ระยะห่าง และการผูกเหล็กเสริมพื้น",
        "category": "reinforcement",
        "stage": "in_progress",
        "order": 6
      },
      {
        "title": "ตรวจสอบแบบหล่อและค้ำยัน",
        "description": "ตรวจสอบความมั่นคงของแบบหล่อและระบบค้ำยัน",
        "category": "formwork",
        "stage": "in_progress",
        "order": 7
      },
      {
        "title": "ตรวจสอบคุณภาพคอนกรีต",
        "description": "ตรวจสอบ Slump Test และการทำ Test Cube",
        "category": "concrete",
        "stage": "in_progress",
        "order": 8
      },
      {
        "title": "ตรวจสอบการเทคอนกรีต",
        "description": "ตรวจสอบกระบวนการเทและการบ่มคอนกรีต",
        "category": "concrete",
        "stage": "in_progress",
        "order": 9
      },
      {
        "title": "ตรวจสอบการถอดแบบ",
        "description": "ตรวจสอบระยะเวลาและวิธีการถอดแบบ",
        "category": "formwork",
        "stage": "post",
        "order": 10
      },
      {
        "title": "ตรวจสอบผิวคอนกรีต",
        "description": "ตรวจสอบรอยแตกร้าว รูพรุน และความเรียบของผิว",
        "category": "finishing",
        "stage": "post",
        "order": 11
      },
      {
        "title": "ตรวจสอบขนาดและระดับโครงสร้าง",
        "description": "ตรวจสอบความถูกต้องของขนาดและระดับโครงสร้าง",
        "category": "dimension",
        "stage": "post",
        "order": 12
      }
    ]
  },
  {
    "name": "งานสถาปัตย์ - Architectural Work",
    "description": "แบบฟอร์มตรวจสอบงานสถาปัตย์และตกแต่ง",
    "category": "architectural",
    "items": [
      {
        "title": "ตรวจสอบแบบสถาปัตย์",
        "description": "ตรวจสอบความถูกต้องของแบบสถาปัตย์และรายละเอียด",
        "category": "documentation",
        "stage": "pre",
        "order": 1
      },
      {
        "title": "ตรวจสอบวัสดุก่ออิฐ",
        "description": "ตรวจสอบคุณภาพและขนาดของอิฐก่อสร้าง",
        "category": "material",
        "stage": "pre",
        "order": 2
      },
      {
        "title": "ตรวจสอบการก่ออิฐผนัง",
        "description": "ตรวจสอบความตรง ความสูง และรอยต่อของผนังอิฐ",
        "category": "masonry",
        "stage": "in_progress",
        "order": 3
      },
      {
        "title": "ตรวจสอบการฉาบปูน",
        "description": "ตรวจสอบความเรียบและความหนาของปูนฉาบ",
        "category": "plastering",
        "stage": "in_progress",
        "order": 4
      },
      {
        "title": "ตรวจสอบการติดตั้งวงกบประตูหน้าต่าง",
        "description": "ตรวจสอบความตรงและระดับของวงกบ",
        "category": "doors_windows",
        "stage": "in_progress",
        "order": 5
      },
      {
        "title": "ตรวจสอบการติดตั้งบานประตูหน้าต่าง",
        "description": "ตรวจสอบการเปิดปิดและอุปกรณ์ประกอบ",
        "category": "doors_windows",
        "stage": "in_progress",
        "order": 6
      },
      {
        "title": "ตรวจสอบงานปูกระเบื้อง",
        "description": "ตรวจสอบความเรียบ รอยต่อ และการเทระดับ",
        "category": "tiling",
        "stage": "in_progress",
        "order": 7
      },
      {
        "title": "ตรวจสอบงานทาสี",
        "description": "ตรวจสอบความเรียบและความสม่ำเสมอของสี",
        "category": "painting",
        "stage": "in_progress",
        "order": 8
      },
      {
        "title": "ตรวจสอบงานฝ้าเพดาน",
        "description": "ตรวจสอบความเรียบและระดับของฝ้าเพดาน",
        "category": "ceiling",
        "stage": "in_progress",
        "order": 9
      },
      {
        "title": "ตรวจสอบงานพื้นผิว",
        "description": "ตรวจสอบความเสียหายและความสะอาดของพื้นผิว",
        "category": "finishing",
        "stage": "post",
        "order": 10
      },
      {
        "title": "ตรวจสอบการทำความสะอาด",
        "description": "ตรวจสอบความสะอาดของงานสถาปัตย์ทั้งหมด",
        "category": "cleanliness",
        "stage": "post",
        "order": 11
      }
    ]
  },
  {
    "name": "งานระบบ - MEP Systems",
    "description": "แบบฟอร์มตรวจสอบงานระบบไฟฟ้า ประปา และสุขาภิบาล",
    "category": "mep",
    "items": [
      {
        "title": "ตรวจสอบแบบระบบไฟฟ้า",
        "description": "ตรวจสอบความถูกต้องของแบบระบบไฟฟ้า",
        "category": "documentation",
        "stage": "pre",
        "order": 1
      },
      {
        "title": "ตรวจสอบแบบระบบประปา",
        "description": "ตรวจสอบความถูกต้องของแบบระบบประปา",
        "category": "documentation",
        "stage": "pre",
        "order": 2
      },
      {
        "title": "ตรวจสอบการฝังท่อร้อยสายไฟ",
        "description": "ตรวจสอบตำแหน่งและขนาดของท่อร้อยสายไฟ",
        "category": "electrical",
        "stage": "in_progress",
        "order": 3
      },
      {
        "title": "ตรวจสอบการติดตั้งตู้สวิตช์บอร์ด",
        "description": "ตรวจสอบตำแหน่งและการติดตั้งตู้สวิตช์บอร์ด",
        "category": "electrical",
        "stage": "in_progress",
        "order": 4
      },
      {
        "title": "ตรวจสอบการเดินสายไฟ",
        "description": "ตรวจสอบขนาดและการเดินสายไฟตามแบบ",
        "category": "electrical",
        "stage": "in_progress",
        "order": 5
      },
      {
        "title": "ตรวจสอบการติดตั้งสวิตช์และเต้ารับ",
        "description": "ตรวจสอบตำแหน่งและความสูงของสวิตช์และเต้ารับ",
        "category": "electrical",
        "stage": "in_progress",
        "order": 6
      },
      {
        "title": "ตรวจสอบการติดตั้งท่อประปา",
        "description": "ตรวจสอบขนาดและการติดตั้งท่อประปา",
        "category": "plumbing",
        "stage": "in_progress",
        "order": 7
      },
      {
        "title": "ตรวจสอบการทดสอบความดันท่อประปา",
        "description": "ตรวจสอบการทดสอบความดันและการรั่วซึมของท่อ",
        "category": "plumbing",
        "stage": "in_progress",
        "order": 8
      },
      {
        "title": "ตรวจสอบการติดตั้งท่อระบายน้ำ",
        "description": "ตรวจสอบความลาดและการต่อท่อระบายน้ำ",
        "category": "drainage",
        "stage": "in_progress",
        "order": 9
      },
      {
        "title": "ตรวจสอบการติดตั้งอุปกรณ์สุขภัณฑ์",
        "description": "ตรวจสอบการติดตั้งและการทำงานของอุปกรณ์สุขภัณฑ์",
        "category": "sanitary",
        "stage": "in_progress",
        "order": 10
      },
      {
        "title": "ทดสอบระบบไฟฟ้า",
        "description": "ทดสอบการทำงานของระบบไฟฟ้าทั้งหมด",
        "category": "testing",
        "stage": "post",
        "order": 11
      },
      {
        "title": "ทดสอบระบบประปา",
        "description": "ทดสอบการทำงานของระบบประปาทั้งหมด",
        "category": "testing",
        "stage": "post",
        "order": 12
      },
      {
        "title": "ทดสอบระบบระบายน้ำ",
        "description": "ทดสอบการระบายน้ำและการไหลของน้ำ",
        "category": "testing",
        "stage": "post",
        "order": 13
      }
    ]
  }
]